dropbox_test_api_implicit/__init__.py
dropbox_test_api_implicit/api_helper.py
dropbox_test_api_implicit/configuration.py
dropbox_test_api_implicit/decorators.py
dropbox_test_api_implicit/dropbox_test_api_implicit_client.py
dropbox_test_api_implicit/controllers/__init__.py
dropbox_test_api_implicit/controllers/base_controller.py
dropbox_test_api_implicit/controllers/files_controller.py
dropbox_test_api_implicit/exceptions/__init__.py
dropbox_test_api_implicit/exceptions/api_exception.py
dropbox_test_api_implicit/http/__init__.py
dropbox_test_api_implicit/http/http_call_back.py
dropbox_test_api_implicit/http/http_client.py
dropbox_test_api_implicit/http/http_context.py
dropbox_test_api_implicit/http/http_method_enum.py
dropbox_test_api_implicit/http/http_request.py
dropbox_test_api_implicit/http/http_response.py
dropbox_test_api_implicit/http/requests_client.py
dropbox_test_api_implicit/models/__init__.py
dropbox_test_api_implicit/models/o_auth_scope_enum.py
dropbox_test_api_implicit/models/response.py
dropbox_test_api_implicit-1.0.dist-info/LICENSE
dropbox_test_api_implicit-1.0.dist-info/METADATA
dropbox_test_api_implicit-1.0.dist-info/WHEEL
dropbox_test_api_implicit-1.0.dist-info/top_level.txt
dropbox_test_api_implicit-1.0.dist-info/RECORD
